vtil/__init__.py
vtil/vtil.so
vtil/arch/__init__.py
vtil/common/__init__.py
vtil/compiler/__init__.py
vtil/symex/__init__.py
VTIL-0.0.3.dist-info/LICENSE
VTIL-0.0.3.dist-info/METADATA
VTIL-0.0.3.dist-info/WHEEL
VTIL-0.0.3.dist-info/top_level.txt
VTIL-0.0.3.dist-info/zip-safe
VTIL-0.0.3.dist-info/RECORD
