Metadata-Version: 2.1
Name: VTIL
Version: 0.0.3
Summary: Virtual-machine Translation Intermediate Language
Home-page: https://github.com/vtil-project/VTIL-Python
Author: Daniel. (@L33T)
License: BSD 3-Clause "New" or "Revised" License
Keywords: VTIL,VTIL Project,vtil,Virtual-machine Translation Intermediate Language,Translation Intermediate Language,Intermediate Language
Platform: UNKNOWN
Classifier: Programming Language :: Python :: 3.4
Classifier: Programming Language :: Python :: 3.5
Classifier: Programming Language :: Python :: 3.6
Classifier: Programming Language :: Python :: 3.7
Classifier: Programming Language :: Python :: 3.8
Classifier: Programming Language :: Python :: 3.9
Classifier: Development Status :: 3 - Alpha
Classifier: Natural Language :: English
Classifier: Operating System :: MacOS
Classifier: Operating System :: POSIX :: Linux
Classifier: Operating System :: Microsoft :: Windows
Classifier: Programming Language :: C++
Classifier: Topic :: Education
Requires-Python: >=3.4
Requires-Dist: pybind11
